{"1":[["1998-99 Philadelphia 76ers","re-signed player","Rick Mahorn"],["ere are the extracted triplets from the text:\n\n Triplets:<1998-99 Philadelphia 76ers","season type","lockout"],["1998-99 Philadelphia 76ers","signed players","Matt Geiger"]],"2":[["ere are the extracted triplets:\n\n<1998-99 Philadelphia 76ers","traded","Tim Thomas"],["1998-99 Philadelphia 76ers","received","Tyrone Hill"],["1998-99 Philadelphia 76ers","traded","Scott Williams"]],"3":[["<1998-99 Philadelphia 76ers season","recorded","28\u201322 record"],["ere are the extracted triplets from the text:\n\n--------------------\n<1998-99 Philadelphia 76ers season","recorded","first winning month"]],"4":[["1998-99 Philadelphia 76ers season","season",""],["ere are the extracted triplets:\n\n<Allen Iverson","led the league in","scoring"]],"5":[["Philadelphia 76ers","lost to","Indiana Pacers"],["ere are the extracted triplets:\n\n<1998-99 Philadelphia 76ers season","won against","Orlando Magic"]],"6":[["ere are the extracted triplets:\n\n<Philadelphia 76ers","season","1998-99"]]}