{"1":[["--------------------\nText: 2009 Kids' Choice Awards:  Dwayne Johnson hosted this awards show which lasted for more than one and half hours.\nTriplets:<Dwayne Johnson","hosted","this awards show"]],"2":[["--------------------\nText: 2009 Kids' Choice Awards:  Voting commenced on March 2, 2009.\nTriplets:<2009 Kids' Choice Awards","Voting commenced on","March 2, 2009>"]],"4":[["Jonas Brothers","changed","line"],["ere are the extracted triplets:\n\n<The Jonas Brothers","sang","\"Lovebug\""],["2009 Kids' Choice Awards","event name","Awards"]],"5":[["--------------------\n<Text: 2009 Kids' Choice Awards: By the end of the program, they were named the \"slime gods\".>\nTriplets:<2009 Kids' Choice Awards","named as","slime gods"]],"7":[["--------------------\nText: 2009 Kids' Choice Awards:  The Nickelodeon Blimp was not used on the Kids' Choice Awards logo again until 2013.\nTriplets:<2009 Kids' Choice Awards","year","2009"],["The Nickelodeon Blimp","used on","Kids' Choice Awards logo"]]}