{"1":[["ere are the extracted triplets:\n\n--------------------\n<Aalborghus Gymnasium","offers","three-year program"],["Aalborghus Gymnasium","offers","two-year Higher Preparatory Examination"]],"2":[["Aalborghus Gymnasium","subject","Spanish"],["ere are the extracted triplets:\n\n<Aalborghus Gymnasium","subject","Religion"],["Aalborghus Gymnasium","subject","Natural Geography"],["Aalborghus Gymnasium","subject","Music"]],"3":[["Aalborghus Gymnasium","perspective on","issue"],["ere are the extracted triplets:\n\nAalborghus Gymnasium","focuses on","musical and creative sid"]],"4":[["ere are the triplets extracted from the text:\n\n<Students","start at","Aalborghus"],["Students","select a","stream of studies"]],"5":[["Each stream","subjects","focus of the studies"],["--------------------\nText: Aalborghus Gymnasium:  Each stream has two or three subjects that are the focus of the studies.\nTriplets:<Each stream","has","two or three"]],"6":[["ere are the extracted triplets:\n\nAalborghus Gymnasium","stream","English\/Social Studie"]]}