{"0":[["<advice column","presented in","magazine or newspaper"],["<advice column","delivered through","internet and broadcast news media"]],"1":[["--------------------\nText: Advice column:\nTriplets:<The advice column","format","question and answer"]],"2":[["--------------------\nText: Advice column:  The responses are written by an advice columnist (colloquially known in British English as an agony aunt, or agony uncle if the columnist is male).\nTriplets:<advice column","written by","advice columnist"]],"3":[["ere are the extracted triplets:\n\n--------------------\n<Advice column","image","older woman"],["<Aunt","image","dispensing comforting advice"],["<Aunt","image","maternal wisdom"]],"4":[["--------------------\nText: Advice column:  An advice columnist can also be someone who gives advice to people who send in problems to the newspaper.\nTriplets:<advice columnist","also be","someone"]]}