{"0":[["ere is the extracted triplet:\n\n\"<The Akron Zips","represent","University of Akron"],["The Akron Zips","located","Ohio"],["The Akron Zips","located","Akron"]],"1":[["--------------------\nText: Akron Zips:  United States.\nTriplets:<Akron Zips","location","United States"]],"2":[["ere are the extracted triplets:\n\n<Akron Zips","competes in","Football Bowl Subdivision"]],"3":[["ere are the extracted triplets:\n\n<Akron Zips","been members of","Mid-American Conference"]],"4":[["Akron Zips","league","MAC"],["--------------------\nText: Akron Zips:  A member of the East Division of the MAC, Akron sponsors teams in six men's, ten women's, and one coed NCAA sanctioned sports:\nTriplets:<Akron Zips","division","East"]]}