{"0":[["ere are the triplets:\n\n\"<Alan C. 'Al' Kamil","nationality","American"],["Alan C. 'Al' Kamil","profession","experimental psychologist"]],"1":[["ere are the triplets extracted from the given text:\n\n<Alan Kamil","title","Director"],["<Alan Kamil","employer","University of Nebraska, Lincoln"],["Alan Kamil","title","George Holmes Professor"]],"2":[["Alan Kamil","work focus","adaptive specializations of learning"],["ere are the extracted triplets:\n\n<Alan Kamil","work focus","evolution of memory"],["Alan Kamil","studied species","Clark's nutcracker"]],"3":[["Kamil","studies of","animal learning and memory"],["ere are the extracted triplets:\n\n<Kamil","published on","peer reviewed articles"]],"4":[["ere are the extracted triplets:\n\n<Alan Kamil","year honored","2013"]]}