{"0":[["Arielle Dombasle","occupation","director"],["Arielle Dombasle","nationality","American-born"],["ere are the extracted triplets:\n\n<Arielle Dombasle","born in","April 27, 1953"],["Arielle Dombasle","occupation","singer"],["Arielle Dombasle","occupation","model"],["Arielle Dombasle","occupation","actress"]],"1":[["Arielle Dombasle","breakthrough films","Alain Robbe-Grillet's"],["--------------------\nText: Arielle Dombasle:  Her breakthrough roles were in \u00c9ric Rohmer's \"Pauline at the Beach\" (1983) and Alain Robbe-Grillet's \"The Blue Villa\" (1995).\nTriplets:<Arielle Dombasle","breakthrough films","\u00c9ric Rohmer's"]],"2":[["< Arielle Dombasle","TV show appearance","Miami Vice"],["ere are the triplets extracted from the text:\n\n< Arielle Dombasle","best known for","American audiences"],["< Arielle Dombasle","character name","Kelly"]],"3":[["--------------------\nText: Arielle Dombasle:  The episode was entitled \"Definitely Miami\".\nTriplets:<Arielle Dombasle","episode title","Definitely Miami"]],"5":[["rielle Dombasle","released","nine album"],["ere are the extracted triplets:\n\nArielle Dombasle","released","twenty single"]]}