{"0":[["<The Austin School of Film","location","Tillery Street"]],"1":[["Austin Cinemaker Co-op","founded","1996"],["--------------------\nText: Austin School of Film:  The Austin School of Film began its start in 2002 under the non-profit umbrella name of Motion Media Arts Center and by merging of the Austin Cinemaker Co-op (founded 1996) and the Center for Young Cinema (founded 1999).\nTriplets:<The Austin School of Film","started","2002"],["Center for Young Cinema","founded","1999"]],"2":[["Austin School of Film","goal","develop"],["Austin School of Film","goal","train"],["ere are the extracted triplets:\n\n<Austin School of Film","goal","educate"]],"3":[["Austin School of Film","program features","graphic design"],["ere are the extracted triplets:\n\n<Austin School of Film","program features","film"],["Austin School of Film","program features","coding"]],"4":[["students","complete","series of courses"],["students","develop","technical skills"],["ere are the extracted triplets:\n\n<They","offer","certificate programs"],["Austin School of Film","programs","Digital Video Certificate Program"]]}