{"0":[["<Baa, Baa, Black Sheep","date","1731>\n<br><br>(since there's only one piece of information about \"Baa, Baa, Black Sheep\", I can't extract a triplet"]],"2":[["Baa, Baa, Black Sheep","melody origin","French"],["--------------------\nText: Baa, Baa, Black Sheep:  It is sung to a variant of the 1761 French melody \"Ah!\nTriplets:<Baa, Baa, Black Sheep","year written","1761"]],"6":[["Baa, Baa, Black Sheep","topic","political correctness"],["Baa, Baa, Black Sheep","subject","controversies"],["--------------------\nText: Baa, Baa, Black Sheep:\nTriplets:<Baa, Baa, Black Sheep","century","twentieth"]],"7":[["Baa, Baa, Black Sheep","usage","popular culture"],["--------------------\nText: Baa, Baa, Black Sheep:  It has been used in literature and popular culture as a metaphor and allusion.\nTriplets:<Baa, Baa, Black Sheep","usage","literature"]],"8":[["--------------------\nText: Baa, Baa, Black Sheep:  The Roud Folk Song Index classifies the lyrics and their variations as number 4439.\nTriplets:<The Roud Folk Song Index","classifies","number 4439"]]}