{"0":[["Rebecca Ferguson","taken as","lead single"],["ere are the extracted triplets:\n\n<Rebecca Ferguson","recorded","song"]],"1":[["--------------------\nText: Backtrack (song):  The song was written by Ferguson and Jonny Lattimer, who produced the track with Tim Baxter as well.\n\nTriplets:<Backtrack","writers","Ferguson"],["Backtrack","writers","Jonny Lattimer"]],"2":[["ere are the triplets extracted from the text:\n\n<Backtrack","release date","14 October 2012"],["Backtrack","location","United Kingdom"]],"3":[["--------------------\nText: Backtrack (song):  The single already features as a bonus track on the U.S. version of \"Heaven\".\nTriplets:<Backtrack","features as","bonus track"]],"4":[["Backtrack","contains elements of","pop"],["3. Text: Backtrack (song):  \"Backtrack\" contains elements of soul, jazz and pop.\nTriplets:\n\n<Backtrack","contains elements of","soul"],["Backtrack","contains elements of","jazz"]]}