{"0":[["--------------------\n<Text: \"Blue Money\" is a song written by Northern Irish singer-songwriter Van Morrison.>\nTriplets:<Van Morrison","nationality","Northern Irish"]],"1":[["Blue Money","album","\"His Band and the Street Choir\""],["Blue Money","chart position","#23"],["ere are the extracted triplets:\n\n<Blue Money","hits","Top Forty"]],"2":[["Blue Money","B-side","\"Astral Weeks\""],["Blue Money","features","\"Sweet Thing\""],["ere are the extracted triplets:\n\nTriplets:<Blue Money","features","single"],["Blue Money","from","album"]],"3":[["ere are the extracted triplets:\n\n--------------------\n<Blue Money","released","single"],["Blue Money","released","UK"]],"4":[["--------------------\nText: Blue Money:  The song became Morrison's third best selling single of the 1970s, remaining on the charts for three months.\nTriplets:<Morrison","best selling single","third"],["song","remaining on charts","three months"]]}