{"0":[["<Bon App\u00e9tit","publisher","Cond\u00e9 Nast"]],"1":[["--------------------\nText: Bon App\u00e9tit:  It was started in 1956.\nTriplets:<Bon App\u00e9tit","started","in 1956"]],"2":[["Bon App\u00e9tit","location","Chicago"],["Bon App\u00e9tit","became","December"],["ere are the extracted triplets:\n\n--------------------\n<Bon App\u00e9tit","published frequency","bimonthly"]],"3":[["Bon App\u00e9tit","location","Kansas City"],["ere are the extracted triplets:\n\nBon App\u00e9tit","acquired by","M. Frank Jones"],["Bon App\u00e9tit","year acquired","1965"]],"4":[["ere are the triplets extracted from the given text:\n\n<Text: Bon App\u00e9tit","owner","Jones"],["Bon App\u00e9tit","editor",""],["Bon App\u00e9tit","publisher","until 1970"]],"6":[["--------------------\nText: Bon App\u00e9tit:  Its sister publication was \"Gourmet\", before the latter was discontinued in October 2009.\nTriplets:<Bon App\u00e9tit","sister publication","Gourmet"]],"7":[["Bon App\u00e9tit","previous headquarters location","New York City"],["ere are the extracted triplets:\n\n<Bon App\u00e9tit","headquarters location","Los Angeles"]]}