{"0":[["--------------------\nText: The Bulldog is a medium-sized breed of dog commonly referred to as the English Bulldog or British Bulldog.\nTriplets:<The Bulldog","commonly referred to as","English Bulldog"],["The Bulldog","also referred to as","British Bulldog"]],"1":[["Bulldog","Other scent-hound breed","Bluetick Coonhound"],["Bulldog","Other scent-hound breed","Irish Wolfhound"],["Bulldog","Other scent-hound breed","Basset Hound"],["ere are the extracted triplets:\n\n<Bulldog","Other scent-hound breed","Small Greek Domestic Dog"],["Bulldog","Other scent-hound breed","Finnish Lapphund"]],"2":[["--------------------\nText: Bulldog:  The Bulldog is a muscular, hefty dog with a wrinkled face and a distinctive pushed-in nose.\nTriplets:<Bulldog","description","muscular"],["Bulldog","feature","pushed-in nose"],["Bulldog","feature","wrinkled face"],["Bulldog","description","hefty"]],"3":[["United Kennel Club","oversees","breeding records"],["ere are the extracted triplets:\n\n<The American Kennel Club","oversees","breeding records"],["The Kennel Club","oversees","breeding records"]],"4":[["ere are the extracted triplets:\n\n--------------------\n<Bulldogs","most popular","US in 2007"],["Bulldogs","rank","fourth"]]}