{"0":[["ere are the extracted triplets:\n\n<Christos V. Konstantakopoulos","nationality","Greek"],["Christos V. Konstantakopoulos","occupation","writer"],["Christos V. Konstantakopoulos","occupation","film producer"]],"1":[["ere are the extracted triplets:\n\n<Text: Christos V. Konstantakopoulos","started producing","2009"],["Christos V. Konstantakopoulos","role","executive producer"],["Christos V. Konstantakopoulos","film","Take Shelter"]],"2":[["<Richard Linklater's \"Before Midnight\"","entry of the","trilogy"],["<Before Midnight","year","2013"],["ere are the extracted triplets:\n\n<Christos V. Konstantakopoulos","produced","Richard Linklater's \"Before Midnight\""]],"3":[["ere are the triplets extracted from the given text:\n\n<Christos V. Konstantakopoulos","made his screenwriting debut","2014"],["<Mikro psari","directed by","Yannis Economides"]],"4":[["Christos V. Konstantakopoulos","film","Love Is Strange"],["ere are the triplets extracted from the text:\n\n<Christos V. Konstantakopoulos","worked on","2014"],["Christos V. Konstantakopoulos","film","Only Lovers Left Alive"]],"5":[["--------------------\nText: Christos V. Konstantakopoulos:  Among his upcoming works as producer or executive producer are Terrence Malick's \"Knight of Cups\" and \"Weightless\" and he has an executive producer credit on \"The Blue Meanie\".\nTriplets:<Christos V. Konstantakopoulos","works","Terrence Malick's \"Knight of Cups\""],["Christos V. Konstantakopoulos","works","\"Weightless\""],["Scott Derrickson","occupation","producer"]]}