{"0":[["The Don River Railway","location","Devonport"],["ere are the triplets extracted from the text:\n\n<Text: The Don River Railway is a volunteer run vintage railway and museum in Don, a suburb of Devonport, Tasmania.>\nTriplets:<The Don River Railway","location","Don"],["The Don River Railway","location","Tasmania"]],"1":[["ere are the triplets extracted from the text:\n\n--------------------\n<Don River Railway","runs from","Don"],["Don River Railway","uses part of","former Don River Line"],["Don River Railway","to","Coles Beach"]],"2":[["Don River Railway","operating days","Sunday"],["ere are the extracted triplets:\n\n--------------------\n<Don River Railway","operating days","Wednesday"]],"3":[["--------------------\nText: Don River Railway:  Don River Railway is open every day except Good Friday and Christmas Day.\nTriplets:<Don River Railway","open days","every day"]],"4":[["ere are the triplets extracted from the text:\n\n--------------------\n<Don River Railway","operates","weekdays"],["Don River Railway","steam locomotives run on","weekends"]],"6":[["<V2","number",""],["<X4","number",""],["<866","number",""],["<Y6","number",""],["ere are the triplets extracted from the text:\n\n--------------------\n<Don River Railway","type of locomotives","diesel"]]}