{"0":[["--------------------\n<Text: The East River is a salt water tidal estuary in New York City.>\nTriplets:<The East River","location","New York City"]],"1":[["ere are the extracted triplets:\n\n<Text:<East River","waterway","connects"],["East River","name","river"]],"2":[["East River","divides","Manhattan"],["ere are the triplets extracted from the text:\n\n<East River","separates","Queens"],["East River","separates","Bronx"]],"3":[["--------------------\nText: East River:  Because of its connection to Long Island Sound, it was once also known as the \"Sound River\".\nTriplets:<East River","also known as","the \"Sound River\""]],"4":[["East River","accentuated by","narrowness and variety of depths"],["ere are the extracted triplets:\n\n--------------------\n<East River","direction of flow","frequently"],["East River","subject to","strong fluctuations"]]}