{"0":[["ere are the triplets:\n\n<Text:The Ford Mondeo MK III","model","second generation"],["The Ford Mondeo MK III","launched by","Ford"],["The Ford Mondeo MK III","launched date","October 2000"]],"1":[["ere are the extracted triplets:\n\n<Ford Mondeo","generation","second"],["Ford","design theme","New Edge"],["Mondeo","predecessor size comparison","larger than"]],"3":[["ere are the extracted triplets:\n\n<Ford Mondeo","generation","second"],["Ford Mondeo","weaknesses","uncompetitive diesel version"],["Ford Mondeo","weaknesses","modest rear legroom"]],"4":[["Ford Mondeo","predecessor's reputation","class leading"],["ere are the extracted triplets:\n\n<Ford Mondeo","basic chassis and suspension design","carried over"]],"5":[["ere are the extracted triplets:\n\n<Ford Mondeo","replaced","Ford Contour"],["Ford Mondeo","replaced by","Ford Fusion"],["Ford Mondeo","sold from","2001"]],"6":[["<Scott Derrickson","nationality","American"]]}