{"0":[["--------------------\nText: Fortress Investment Group is an investment management firm based in New York City.\nTriplets:<Fortress Investment Group","based in","New York City"]],"1":[["ere are the extracted triplets:\n\n<Fortress Investment Group","launched on","February 9, 2007"],["<Fortress Investment Group","underwriters","Goldman Sachs"]],"2":[["Fortress Investment Group","assets types","private equity"],["ere are the triplets extracted from the text:\n\n<Fortress Investment Group","managed","approximately"],["Fortress Investment Group","assets types","credit funds"],["Fortress Investment Group","assets types","liquid hedge funds"],["Fortress Investment Group","amount","$70.2 billion"]],"3":[["--------------------\nText: Fortress Investment Group:  In 2014, Fortress Investment Group was named \"Hedge Fund Manager of the Year\" by \"Institutional Investor\" and \"Management Firm of the Year\" by \"HFMWeek\".\nTriplets:<Fortress Investment Group","award","\"Hedge Fund Manager of the Year\""],["Fortress Investment Group","award","\"Management Firm of the Year\""]],"4":[["<Fortress Investment Group","year","2012"],["<Fortress Investment Group","year","2011"],["<Fortress Investment Group","year","2010"]]}