{"0":[["The Georges Head Battery","location","Mosman"],["The Georges Head Battery","location","Sydney"],["ere are the extracted triplets:\n\n<The Georges Head Battery","location","Georges Head"]],"2":[["ere are the extracted triplets:\n\n--------------------\n<Georges Head Battery","location","area"]],"3":[["--------------------\nText: Georges Head Battery:  The other two forts are located at Middle Head and Bradleys Head, Mosman.\nTriplets:<Georges Head Battery","located at","Middle Head"],["Georges Head Battery","located at","Bradleys Head"]],"4":[["--------------------\nText: Georges Head Battery:  The fort became a command post in the 1890s for the coordination of all of Sydney's harbour defences.\nTriplets:<Georges Head Battery","purpose","command post"]],"5":[["ere are the extracted triplets:\n\n<Georges Head Battery","decommissioned year","2002"],["<Georges Head Battery","managed by","Sydney Harbour Federation Trust"],["<Georges Head Battery","managed by","NSW National Parks & Wildlife Service"]]}