{"0":[["--------------------\nText: Gotas de Rap (\"Drops of Rap\") were a Colombian rap group from Bogot\u00e1.\nTriplets:<Gotas de Rap","origin","Colombian"],["Gotas de Rap","from","Bogot\u00e1"]],"1":[["--------------------\nText: Gotas de Rap:  They toured Europe in 1995 and in their songs they rapped in Spanish about the social and political problems in Colombia.\nTriplets:<Gotas de Rap","toured","Europe"],["Gotas de Rap","rapping about","social and political problems in Colombia"]],"2":[["ere are the extracted triplets:\n\n--------------------\n<Gotas de Rap","group type","pioneers"]],"3":[["ere are the triplets extracted from the text:\n\n--------------------\n<They","success","among"],["controversial lyrics","had","new breed of music"],["ghettos and rappers","had","huge"]],"4":[["ere are the triplets extracted from the given text:\n\n--------------------\n<Gotas de Rap","Hip-hop genre","came to its peak in 2002"]]}