{"0":[["Grant County PUD","type","public utility district"],["ere are the extracted triplets:\n\n<Text: Public Utility District No. 2 of Grant County, or Grant County PUD, is a public utility district in north central Washington state.>\n<Triplets:<Public Utility District No. 2 of Grant County","location","Washington state"]],"1":[["Grant County Public Utility District","owned by","customers"],["Grant County Public Utility District","elected by","customer-owners"],["--------------------\n<Text: Grant County Public Utility District:  It is owned by its customers and governed by a Board of Commissioners elected by the customer-owners.>\nTriplets:<Grant County Public Utility District","governed by","Board of Commissioners"]],"2":[["ere are the extracted triplets:\n\n<Grant County Public Utility District","type","nonprofit corporation"],["a PUD","regulation","by state statute"]],"5":[["Grant County Public Utility District","operates","Wanapum Dam"],["Grant County Public Utility District","operates","Priest Rapids Dam"],["ere are the extracted triplets:\n\n<Grant County Public Utility District","operates","hydroelectric projects"]],"6":[["<Grant County Public Utility District","operates","Potholes East Canal Headworks Project"],["ere are the extracted triplets:\n\n<Grant County Public Utility District","operates","Quincy Chute Hydroelectric Project"],["<Grant County Public Utility District","part of","Nine Canyon Wind Project"]]}