{"0":[["The Greenland Sea","to the","south"],["ere are the extracted triplets:\n\n<The Greenland Sea","borders","Greenland"],["The Greenland Sea","to the","west"],["The Greenland Sea","to the","north"],["The Greenland Sea","to the","east"]],"2":[["--------------------\nText: Greenland Sea:  However, definitions of the Arctic Ocean and its seas tend to be imprecise or arbitrary.\nTriplets:<Greenland Sea","description","arbitrary"]],"3":[["--------------------\nText: Greenland Sea:  In general usage the term \"Arctic Ocean\" would exclude the Greenland Sea.\nTriplets:<Greenland Sea","term excluding","Arctic Ocean"]],"5":[["ere are the extracted triplets:\n\n<Greenland Sea","description","Nordic Seas"],["Nordic Seas","connection","Atlantic"],["Nordic Seas","connection","Arctic"]],"6":[["Arctic Ocean","and","Nordic Seas"],["ere are the triplets extracted from the text:\n\n<Greenland Sea","definition","In oceanography"]]}