{"0":[["ere are the extracted triplets:\n\n<Text:Hanoi","location","Vietnam"],["Hanoi","city type","second largest"],["Hanoi","capital","Socialist Republic of Vietnam"]],"2":[["Hanoi","population size","7.7 million"],["--------------------\nText: Hanoi:  The population in 2015 was estimated at 7.7 million people.\nTriplets:<Hanoi","population in","2015"]],"3":[["--------------------\n<Text: Hanoi:  From 1010 until 1802, it was the most important political centre of Vietnam.>\nTriplets:<Hanoi","years","1010"],["Hanoi","characteristic","most important"],["Hanoi","location","Vietnam"]],"4":[["Vietnam","capital","Hanoi"],["--------------------\nText: Hanoi:  It was eclipsed by Hu\u1ebf, the imperial capital of Vietnam during the Nguy\u1ec5n Dynasty (1802\u20131945), but Hanoi served as the capital of French Indochina from 1902 to 1954.\nTriplets:<Hanoi","was eclipsed by","Hu\u1ebf"],["Shirley Temple","served as","Chief of Protocol"]],"5":[["ere are the extracted triplets:\n\n--------------------\n<From","year","1954"],["Hanoi","capital of","North Vietnam"],["Hanoi","capital of","unified Vietnam"]]}