{"2":[["ere are the triplets extracted from the text:\n\n<Hip Hop Since 1978","involvement","Roc-A-Fella Records"],["Hip Hop Since 1978","operation type","daily operations"]],"3":[["ere are the triplets extracted from the given text:\n\nTriples:<Hip Hop Since 1978","signed","Kanye West"],["Hip Hop Since 1978","label","Roc-A-Fella Records"],["Hip Hop Since 1978","company","production and management"]],"4":[["West","album","The College Dropout"],["<West","project","Hip Hop Since 1978"]],"5":[["--------------------\n<Text: Hip Hop Since 1978:  In January 2007, they partnered with Bryant Entertainment.>\nTriplets:<Hip Hop Since 1978","partnered with","Bryant Entertainment"]],"7":[["Kyambo Joshua","parted ways","in 2009"],["<Kyambo Joshua","and","Columbia Records"]],"8":[["ere are the triplets extracted from the text:\n\n<Most Recently","artist","Young Jeezy"]],"10":[["Kyambo Joshua","worked at","Def Jam Recordings"],["ere are the triplets extracted from the text:\n\n Triplets:<Hip Hop Since 1978","members","Kyambo Joshua"],["Gee Roberson","launched agencies","The Blueprint Group"]]}