{"0":[["ere are the triplets extracted from the text:\n\n<Ife Piankhi","profession","poet"],["Ife Piankhi","profession","singer"],["Ife Piankhi","profession","educator"],["Ife Piankhi","profession","creative facilitator"]],"1":[["Ife Piankhi","collaborated with","Floetry"],["Ife Piankhi","collaborated with","Mamoud Guinea"],["Ife Piankhi","collaborated with","Wynton Marsalis"],["Ife Piankhi","collaborated with","Jonzi D"],["Ife Piankhi","collaborated with","Geoff Wilkinson"],["Ife Piankhi","collaborated with","Nneka"],["--------------------\nText: Ife Piankhi:  She has collaborated with artists such as Keko, Nneka, Mamoud Guinea, Geoff Wilkinson, Michael Franti, Jonzi D, Wynton Marsalis, Floetry, among others.\nTriplets:<Ife Piankhi","collaborated with","Keko"],["Ife Piankhi","collaborated with","Michael Franti"]],"2":[["Ife Piankhi","visited country","Zanzibar"],["Ife Piankhi","visited country","Zambia"],["Ife Piankhi","visited country","Ghana"],["Ife Piankhi","visited country","Romania"],["Ife Piankhi","visited country","Holland"],["ere are the triplets extracted from the text:\n\n<Text: Ife Piankhi","visited country","Canada"],["Ife Piankhi","visited country","Italy"],["Ife Piankhi","visited country","Sierra Leone"]],"3":[["Ife Piankhi","related to","Henry Bonsu"],["Ife Piankhi","related to","Colourful Radio"],["ere are the triplets extracted from the text:\n\n<If e Piankhi","lived in","London"]],"4":[["ere are the triplets extracted from the text:\n\n<Ife Piankhi","featured in","500 years later"],["Ife Piankhi","featured in","Nubian Spirit"]],"5":[["If\u0435 Piankhi","event","Poetry in Session"],["ere are the extracted triplets:\n\n<If\u0435 Piankhi","occupation","resident poet"],["If\u0435 Piankhi","location","Kampala"]]}