{"0":[["INXS","place of formation","Sydney"],["<INXS","formed as","The Farriss Brothers"]],"1":[["--------------------\n<Text: INXS:  They began playing covers in Western Australian pubs and clubs, occasionally playing some of their original music.>\n\n<INXS","began doing","covers"]],"2":[["INXS","mainstays member","Jon Farriss"],["ere are the triplets extracted from the text:\n\n<INXS","mainstays member","Andrew Farriss"],["INXS","mainstays member","Michael Hutchence"]],"3":[["ere are the extracted triplets:\n\n<INXS","fronted by","Hutchence"]],"4":[["Text: INXS","style","pub rock"],["Text: INXS","influenced by","funk and dance"],["ere are the extracted triplets:\n\n<Text: INXS","style","new wave\/pop"]]}