{"0":[["<Jane Marum Roush","occupation","Judge"],["<Jane Marum Roush","nationality","Virginia"],["ere are the extracted triplets:\n\n<Jane Marum Roush","born in","September 24, 1956"],["<Jane Marum Roush","occupation","lawyer"]],"1":[["<Terry McAuliffe","position","Governor"],["<LeRoy F. Millette, Jr.","position","Justice"],["ere are the triplets extracted from the text:\n\n<Jane Marum Roush","appointment date","July 27, 2015"]],"2":[["Virginia General Assembly","session type","next session"],["Virginia General Assembly","session duration","thirty days"],["ere are the extracted triplets:\n\n<Jane Marum Roush","appointment status","interim"]],"3":[["Jane Marum Roush","event type","General Assembly convened in special session"],["--------------------\nText: Jane Marum Roush:\nTriplets:<Jane Marum Roush","event date","August 17, 2015"]],"4":[["The Constitution","prohibits","three days"],["The Constitution","prohibits","one chamber"],["ere are the triplets extracted from the text:\n\n<Jane Marum Roush","quote","The Constitution"]],"5":[["--------------------\nText: Jane Marum Roush:  The Governor claims that this provision applies only to regular sessions of the General Assembly; the House of Delegates and most Senate Republicans claim it applies to special sessions as well, and that the Senate's adjournment was invalid because the House did not consent.\nTriplets:<Governor","claim","this provision"],["most Senate Republicans","claim","it applies"],["House of Delegates","claim","it applies"]],"7":[["ere are the extracted triplets:\n\n<Jane Marum Roush","title",""]],"9":[["ere are the extracted triplets:\n\n<Jane Marum Roush","expiration date","February 12, 2016"],["Jane Marum Roush","start of regular session","January 13"]]}