{"0":[["Jeff \"Flash\" Malcolm","birthplace","Cowra, New South Wales"],["Jeff \"Flash\" Malcolm","profession","Australian professional boxer"],["ere are the triplets extracted from the text:\n\n<Jeff \"Flash\" Malcolm","born","May 9, 1956"]],"1":[["ere are the extracted triplets:\n\n<Jeff Malcolm","won the","Australian light welterweight title"],["<Jeff Malcolm","won the","World Boxing Federation (WBF) Intercontinental welterweight title"],["<Jeff Malcolm","won the","South Pacific light welterweight title"]],"2":[["<Jeff Malcolm","challenged for","World Boxing Organization (WBO) welterweight title"],["<Jeff Malcolm","challenged for","Australian welterweight title"],["ere are the triplets extracted from the text:\n\n<Jeff Malcolm","challenged for","South Seas light welterweight title"]],"3":[["ere are the extracted triplets:\n\n<Jeff Malcolm","professional fighting weight","135 lb"],["Jeff Malcolm","professional fighting weight","super middleweight"]],"4":[["--------------------\n<Text: Jeff Malcolm:  He was inducted into the Australian National Boxing Hall of Fame in 2007.>\nTriplets:<Jeff Malcolm","inducted into","Australian National Boxing Hall of Fame"]]}