{"0":[["ere are the triplets:\n\n<Text: Jeonju Hanok Village","located in","Jeonju"],["Text: Jeonju Hanok Village","location","South Korea"]],"1":[["--------------------\nText: Jeonju Hanok Village:  The village contains over 800 Korean traditional houses called 'Hanok'.\nTriplets:<Jeonju Hanok Village","contains","over 800"],["Jeonju Hanok Village","traditional houses called","Hanok"]],"2":[["ere are the extracted triplets:\n\n<Jeonju Hanok Village","famous among","Koreans"],["Jeonju Hanok Village","traditional buildings","strongly contrast"]],"3":[["<Jeonju Hanok Village","recognition","2010"],["ere are the triplets extracted from the given text:\n\n<Jeonju Hanok Village","designated as","International Slow City"],["<Jeonju Hanok Village","blend of","traditional culture and nature"]],"4":[["Text: Jeonju Hanok Village:\nTriplets:<Jeonju Hanok Village","visitors increased","2000s"]],"5":[["ere are the extracted triplets:\n\n<Jeonju Hanok Village","visitor numbers","more than doubled"],["Jeonju Hanok Village","year of increase","2007"],["Jeonju Hanok Village","year of increase","2014"]],"6":[["ere are the extracted triplets:\n\n<triplets><Jeonju","ranked as","third"],["Jeonju","compared to","Jeju"],["Jeonju","compared to","Seoul"]]}