{"0":[["ere are the extracted triplets:\n\n<Kansas City Scout","description","one of the United States' largest electronic traffic management systems"]],"1":[["Kansas City Scout","initiative between","Missouri Department of Transportation"],["Kansas City Scout","initiative between","Kansas Department of Transportation"],["ere are the extracted triplets:\n\n*Kansas City Scout","created","2000"]],"4":[["Kansas City Scout","shared by","MoDOT"],["--------------------\n\n--------------------\n<Kansas City Scout","shared by","KDOT"]],"6":[["--------------------\nText: Kansas City Scout:  While the system has extensive coverage of highways in the Kansas City Metropolitan Area it still has much more to cover.\n\nTriplets:<Kansas City Scout","has coverage of","highways"],["Kansas City Scout","location","Kansas City Metropolitan Area"]],"7":[["ere are the extracted triplets:\n\n--------------------\n<Since","it would be too expensive","to cover all the major highways"],["<Kansas City metro","has more miles of highway per person","than any other metropolitan area"],["<highways or segments of highways","have priority","due to higher accident rates"]],"8":[["Kansas City Scout","future action","continue to expand"],["--------------------\nText: Kansas City Scout:  Since the project's beginning, it has expanded greatly, and will continue to expand.\nTriplets:<Kansas City Scout","project status","expanded"]],"10":[["Kansas City Scout","located at","Penn Valley Park"],["ere are the extracted triplets:\n\n<Kansas City Scout","named after","Kansas City Scout Statue"]]}