{"0":[["Kim Jong-hyun","occupation","radio host"],["Kim Jong-hyun","nationality","South Korea"],["ere are the triplets extracted from the text:\n\nKim Jong-hyun","born in","1990"],["Kim Jong-hyun","occupation","singer-songwriter"]],"1":[["Kim Jong-hyun","vocalist for","S.M. Entertainment"],["ere are the extracted triplets:\n\n<Kim Jong-hyun","member of","Shinee"]],"2":[["--------------------\nText: Kim Jong-hyun (singer):  The Ballad.\nTriplets:<Kim Jong-hyun","category","singer"]],"3":[["ere are the extracted triplets:\n\n<Kim Jong-hyun","debut date","January 12, 2015"],["Kim Jong-hyun","title of work","\"Base\""]],"4":[["ere are the triplets extracted from the text:\n\n<Kim Jong-hyun","released an album","\"Story Op.1\""]]}