{"0":[["ere are the triplets extracted from the text:\n\n<Kimberly Susan \"Kim\" Rhode","born in","July 16, 1979"],["Kimberly Susan \"Kim\" Rhode","nationality","American"],["Kimberly Susan \"Kim\" Rhode","occupation","skeet shooter"]],"1":[["*Kim Rhode","Olympic achievement","three gold medals"],["ere are the extracted triplets:\n\n*Kim Rhode","native","California"]],"2":[["ere are the extracted triplets:\n\n<Kim Rhode","most successful female shooter","Olympics"],["Kim Rhode","won two Olympic gold medals","Double Trap"],["Kim Rhode","tripple Olympic Champion",""]],"3":[["Kim Rhode","year","2012"],["ere are the extracted triplets:\n\nKim Rhode","won","gold meda"],["Kim Rhode","event","skeet shooting"]],"4":[["<Kim Rhode","won medal at","Rio 2016 Olympics"]]}