{"0":[["Kings Park Speedway","operator","Regina Auto Racing Club"],["ere are the extracted triplets:\n\n<Kings Park Speedway","location","north-east of Regina"],["Kings Park Speedway","location","north-west of Pilot Butte"]],"1":[["ere are the extracted triplets:\n\n<The facility","features a","1\/3 mile"],["Kings Park Speedway","style track","paper clip"]],"2":[["--------------------\nText: Kings Park Speedway:  It is primarily used for stock car racing.\nTriplets:<Kings Park Speedway","used for","stock car racing"]],"3":[["ere are the extracted triplets:\n\nKings Park Speedway:<Originally a dirt oval","was paved","1970"]],"4":[["<Kings Park Speedway","hosted","Baby Grand racing series"],["<Kings Park Speedway","hosted","Pro Trucks"],["<Kings Park Speedway","hosted","Evolution Mini Cup Car series"],["<Kings Park Speedway","hosted","Western Canada Super Late Model Racing Series"],["<Kings Park Speedway","hosted","Legends of Alberta"],["ere are the extracted triplets:\n\n<In 2010 it hosted","40th Anniversary events","Kickin Asphalt"]],"5":[["Kings Park Speedway","held races in","Mini stock classes"],["Kings Park Speedway","held races in","Bomber"],["ere are the extracted triplets:\n\n<Kings Park Speedway","held races in","Street Stock"]],"6":[["Kings Park Speedway","events included","trailer racing"],["--------------------\n<Text: Kings Park Speedway:  2015 special events included Drifting, trailer racing, and wheelies.]\n\nTriplets:<Kings Park Speedway","events included","Drifting"],["Kings Park Speedway","events included","wheelies>"]]}