{"0":[["Malm\u00f6 Arena","home to","SHL ice hockey club Malm\u00f6 Redhawks"],["ere are the extracted triplets:\n\n<Malm\u00f6 Arena","location","Malm\u00f6"],["Malm\u00f6 Arena","type","multi-use indoor"]],"2":[["ere are the triplets extracted from the text:\n\n<hosting","hockey matches","Redhawks"],["Malm\u00f6 Arena","venue for","concerts"],["Malm\u00f6 Arena","venue for","team handball"]],"3":[["--------------------\nText: Malm\u00f6 Arena:\n\nTriplets:<Malm\u00f6 Arena","has hosted","indoor athletics"]],"4":[["Hannu Helki\u00f6","participated in design","P\u00f6yry Architects"],["--------------------\nText: Malm\u00f6 Arena:  Owned and operated by Parkfast AB, the arena was designed by Mats Matson of MM Matsson Konsult AB, Hannu Helki\u00f6 of P\u00f6yry Architects, and Gert Wing\u00e5rdh of Wing\u00e5rdh arkitektkontor.\nTriplets:<Mats Matson","participated in design","MM Matsson Konsult AB"],["Gert Wing\u00e5rdh","participated in design","Wing\u00e5rdh arkitektkontor"]],"6":[["Malm\u00f6 Arena","location","2013"],["ere are the triplets extracted from the text:\n\n<Malm\u00f6 Arena","hosted","Eurovision Song Contest"]]}