{"0":[["--------------------\n<Text: North Ko\u02bb olaupoko is an area in the City & County of Honolulu, Hawaii, United States, on the island of O\u02bb ahu.>\nTriplets:<North Ko\u02bb","location","Hawaii"]],"1":[["<North Koolaupoko","population","778"],["<North Koolaupoko","census year","2010"],["ere are the extracted triplets:\n\n--------------------\n<North Koolaupoko","location","Hawaii"],["<North Koolaupoko","corresponds to","Waikane"]],"2":[["--------------------\nText: North Koolaupoko, Hawaii:  In Hawaiian, \"ko\u02bb olau poko\" means \"short windward\", referring to the fact that this is the shorter of the two windward districts on the island (\"Ko\u02bb olauloa\" or \"long windward\" is the other).\nTriplets:<North Koolaupoko","means","short windward"],["North Koolaupoko","referring to","windward districts"]],"3":[["<Ko\u02bbolaupoko","extends from","Makapu\u02bbu Point"],["ere are the extracted triplets:\n\n--------------------\n<North Koolaupoko","location","Hawaii"]],"4":[["K\u0101ne\u02bb ohe","location","windward towns"],["--------------------\nText: North Koolaupoko, Hawaii:  Included within the district, south of North Ko\u02bb olaupoko, are the largest windward towns of K\u0101ne\u02bb ohe, Kailua, and Waim\u0101nalo.\nTriplets:<North Koolaupoko","location","Hawaii"],["<Kailua","location","windward towns"],["<Waim\u0101nalo","location","windward towns"]]}