{"1":[["ere are the extracted triplets:\n\n<Norwegian County Road 63","begins at","Norwegian National Road 15"],["<Norwegian County Road 63","ends at","junction with European route E136 highway"],["<\u00c5ndalsnes","located in","Rauma Municipality"]],"2":[["ere are the extracted triplets:\n\n<Norwegian County Road 63","route length","103.6 km"]],"3":[["Norwegian County Road 63","portion","Oppland county"],["--------------------\nText: Norwegian County Road 63:  The vast majority of the road is in M\u00f8re og Romsdal county, only the southernmost 2.5 km lie in the extreme western part of Oppland county.\nTriplets:<Norwegian County Road 63","location","M\u00f8re og Romsdal county"],["Norwegian County Road 63","portion","southernmost 2.5 km"]],"4":[["Norwegian County Road 63","weather conditions","snow"],["ere are the extracted triplets:\n\n<Norwegian County Road 63","sections","Langvatnet\u2013Geiranger"],["Norwegian County Road 63","sections","Trollstigen"],["Norwegian County Road 63","weather conditions","avalanches"]],"5":[["--------------------\nText: Norwegian County Road 63: The road passes by a number of notable landmarks, which has led to the earmarking of the route as national tourist route.\n\nTriplets:<Norwegian County Road 63","national tourist route","route"]]}