{"0":[["The Old Dominion Monarchs","competes in","NCAA Division I men's competition"],["ere are the triplets extracted from the text:\n\n<Text>The Old Dominion Monarchs","represent","Old Dominion University"],["The Old Dominion Monarchs","based in","Norfolk, Virginia"]],"1":[["--------------------\nText: Old Dominion Monarchs basketball:  (The women's team, which has traditionally had a considerably higher national profile, is known as the Lady Monarchs.)\nTriplets:<Old Dominion Monarchs","also known as","Lady Monarchs"]],"2":[["ere are the triplets extracted from the text:\n\n Triplets:<Old Dominion Monarchs","competes in","Conference USA>\n\nNote that there is only one triplet extractable from this text"]],"3":[["Old Dominion Monarchs","championships","2009"],["ere are the triplets extracted from the text:\n\n<Old Dominion Monarchs","championships","1975"],["Old Dominion Monarchs","championships","2016"]],"4":[["Old Dominion Monarchs","year",""],["Old Dominion Monarchs","in the","NCAA Tournament"]],"5":[["ere is the extracted triplet:\n\nTriplets:<Old Dominion Monarchs","currently coached by","Jeff Jones"]]}