{"0":[["Paul Johann Ludwig von Heyse","occupation","writer"],["Paul Johann Ludwig von Heyse","nationality","German"],["ere are the extracted triplets:\n\n<Paul Johann Ludwig von Heyse","born","15 March 1830"]],"1":[["Paul Heyse","member of","Die Krokodile"],["ere are the triplets extracted from the text:\n\n<Paul Heyse","member of","Tunnel \u00fcber der Spree"]],"2":[["ere are the extracted triplets:\n\nText: <Paul Heyse","dominant figure","German men of letters"]],"3":[["<Paul Heyse","demonstrated as","lyric poet, dramatist, novelist and writer"],["<Paul Heyse","recognized for","Literature"],["ere are the extracted triplets:\n\n<Paul Heyse","awarded for","Nobel Prize"]],"4":[["ere are the triplets extracted from the text:\n\n<Paul Heyse","quote","Wirsen"]],"5":[["Alice Munro","laureate","Jaroslav Seifert"],["Doris Lessing","laureate","Theodor Mommsen"],["ere are the triplets:\n\n<Paul Heyse","oldest laureate","fifth"]]}