{"0":[["Pignolo","type","Italian wine grape"],["ere are the triplets extracted from the text:\n\n<Text:Pignolo","growing region","Friuli-Venezia Giulia"]],"1":[["ere are the extracted triplets:\n\n--------------------\n<Believed to have been cultivated","in","the hills"],["<Pignolo grape","believed to be from","Rosazzo"],["<Pignolo grape","now a prominent variety","in Colli Orientali del Friuli"]],"2":[["--------------------\n<Text: Pignolo (grape):  In Italian the grape's name originates from \"pigna\" (pine cone), because the grapes are dense like pine cones.>\nTriplets:<Pignolo","originates from","pigna"],["Pignolo","description","dense like pine cones"]],"3":[["Pignolo","mentioned in","book \"Bacchus in Friuli\""],["--------------------\nText: Pignolo (grape):  The first recorded mention of the grape was in Abbot Giobatta Michieli's late 17th century book \"Bacchus in Friuli\" in which he described the grape making \"excellent black wine\".\nTriplets:<Pignolo","first mentioned by","Abbot Giobatta Michieli"]],"5":[["Pignolo (grape)","flavor notes include","blackberry"],["Pignolo (grape)","flavor notes include","plum"],["ere are the triplets extracted from the given text:\n\n<Pignolo (grape)","has good balance between","acidity and tannins"]],"6":[["Pignolo","region","Valtellina"],["--------------------\n<Text: Pignolo (grape):  Most experts believe that it is not related to the Lombardy Pignola grape of the Valtellina region.>\nTriplets:<Pignolo","related to","Lombardy Pignola grape"]]}