{"0":[["The Red Bull RB12","season","2016 Formula One"],["--------------------\nText: The Red Bull RB12 is a Formula One racing car designed by Red Bull Racing to compete in the 2016 Formula One season.\n\nTriplets:<The Red Bull RB12","designed by","Red Bull Racing"]],"1":[["<Daniel Ricciardo","driver","Red Bull RB12"],["Max Verstappen","driver","Red Bull RB12"]],"2":[["Spanish Grand Prix","related event","promoted to Red Bull"],["ere are the triplets extracted from the given text:\n\n<Red Bull RB12","driver","Verstappen"],["Scuderia Toro Rosso","driver","Verstappen"]],"4":[["<Red Bull RB12","rebadged as","TAG Heuer"],["ere are the extracted triplets:\n\n<Red Bull RB12","engine","Renault"]],"5":[["ere are the triplets extracted from the text:\n\n<Red Bull RB12","partner","Total"]]}