{"0":[["< Ringer Hut","dishes","Sara udon"],["< Ringer Hut","specialization","Nagasaki dishes"],["ere are the triplets:\n\n< Ringer Hut","location","Japanese"],["< Ringer Hut","dishes","Champon"]],"1":[["ere are the extracted triplets:\n\n<The Hamakatsu Co.","founders","1974"],["Ringer Hut","name origin","former Ringer House"]],"2":[["--------------------\nText: Ringer Hut:  It is likely that the company borrowed the word \"hut\" from \"Pizza Hut.\"\nTriplets:<Ringer Hut","related to","Pizza Hut"]],"3":[["Ringer Hut","operates in","Taiwan"],["Ringer Hut","operates in","California"],["<Ringer Hut","operates in","Japan"]],"4":[["--------------------\n<Ringer Hut","headquarters location","Fukuoka"],["<Ringer Hut","headquarters location","Tokyo"]]}