{"0":[["<The Social-Democratic Party of Abkhazia","language","Georgian"],["ere are the extracted triplets:\n\n<The Social-Democratic Party of Abkhazia","language","Russian"]],"1":[["ere are the triplets extracted from the text:\n\n<Social-Democratic Party","founded during","crisis"],["Social-Democratic Party","founded during","October 2004 presidential election"],["Sergei Shamba","came third in","election"]],"2":[["<Shamba","member","Gennady Alamia"],["ere are the triplets extracted from the text:\n\n<Shamba","Vice Presidential candidate","Vladimir Arshba"],["<Shamba","member","Albert Topolian"]],"3":[["ere are the triplets extracted from the text:\n\n<Text: Social-Democratic Party of Abkhazia","foundation congress took place on","15 October 2005"],["Social-Democratic Party of Abkhazia","location","State Drama Theatre of Abkhazia"],["Gennadi Alamia","title","first chairman"]],"4":[["--------------------\nText: Social-Democratic Party of Abkhazia:  The Union of Social-Democratic Youth was founded as the party's youth wing, headed by Abkhazian State University student Astamur Logua.\n\nTriplets:<Abkhazian State University","student","Astamur Logua"]]}