{"0":[["Stance","sport","American football"],["--------------------\n<Text: Stance is the position an American football player adopts when a play begins.>\nTriplets:<Stance","definition","position"],["Scott Derrickson","nationality","America"]],"1":[["ere are the extracted triplets:\n\n\"<Stance","common stance","two-point"],["Stance","common stance","four-point"],["Stance","common stance","three-point"]],"2":[["ere are the extracted triplets:\n\n--------------------\n<Stance","definition","The stance names reference the number of points where a player's body is touching the ground while down in the stance"]],"3":[["Text: Stance (American football):  Each technique has its own strengths and weaknesses; therefore, each one is used accordingly in different situations.\nTriplets:<Stance","technique","Each technique"],["Stance","has its own","strengths and weaknesses"],["Scott Derrickson","nationality","America"]],"4":[["Stance","level of competition","college football"],["Stance","level of competition","high school football"],["ere are the extracted triplets:\n\n<Stance","level of competition","little league football"]]}