{"0":[["Stephen P. Halbrook","organization","Independent Institute"],["ere are the extracted triplets:\n\n<Stephen P. Halbrook","title","Senior Fellow"]],"1":[["<Stephen Halbrook","written about","Fourteenth Amendment"],["<Stephen Halbrook","written about","Second Amendment rights"],["ere are the extracted triplets:\n\n<Stephen Halbrook","written about","Second Amendment"]],"2":[["Stephen Halbrook","won cases","\"United States v. Thompson-Center Arms Company\""],["Stephen Halbrook","won cases","\"Castillo v. United States\""],["Stephen Halbrook","won cases","\"Printz v. United States\""],["ere are the triplets extracted from the text:\n\n<Text: Stephen Halbrook","cases won before","US Supreme Court"]],"4":[["ere are the extracted triplets:\n\n<Stephen Halbrook","wrote a brief on behalf of","the majority of both houses of Congress"]],"5":[["Stephen Halbrook","researched on","Second Amendment"],["Stephen Halbrook","decades of","research"],["ere are the triplets extracted from the text:\n\n<Stephen Halbrook","contributed to","the intellectual foundation"]],"6":[["<Stephen Halbrook","cited in","Supreme Court opinions"],["ere are the extracted triplets:\n\n<Stephen Halbrook","written works","books"],["<Stephen Halbrook","written works","articles"],["<Stephen Halbrook","topics","gun control"]],"7":[["--------------------\n<Text: Stephen Halbrook:  He has testified before congress on multiple occasions.>\nTriplets:<Stephen Halbrook","testified before","congress"]],"8":[["Stephen Halbrook","book title","\"That Every Man Be Armed\""],["ere are the extracted triplets:\n\n<Stephen Halbrook","most important scholarly contribution","book"],["Stephen Halbrook","book publication year","1986"]]}