{"2":[["ere are the triplets extracted from the text:\n\n<Stephen Gillett","position","Executive Vice President"],["Stephen Gillett","position","Chief Operating Officer"],["Stephen Gillett","left behind","President Best Buy Digital"]],"3":[["Stephen Gillett","departure date","November 2014"],["--------------------\n<Text: Stephen Gillett:  He departed Symantec in November 2014.>\nTriplets:<Stephen Gillett","departed from","Symantec"]],"4":[["<Stephen Gillett","position","Executive Vice President"],["ere are the triplets extracted from the text:\n\n<Stephen Gillett","position","Chief Information Officer"],["<Stephen Gillett","company","Starbucks Coffee Company"]],"5":[["Stephen Gillett","previously worked at","CNET"],["--------------------\n<Text: Stephen Gillett:  Gillett previously held executive positions at Corbis, Yahoo and CNET.>\nTriplets:<><Stephen Gillett","previously worked at","Corbis"],["Stephen Gillett","previously worked at","Yahoo"]],"6":[["ere are the extracted triplets:\n\n<Stephen Gillett","currently lives and works","Silicon Valley"]]}