{"0":[["S\u00e6berht","alternative names","S\u00e6bert"],["--------------------\nText: S\u00e6berht, Saberht or S\u00e6bert (d. \"c\".\nTriplets:<S\u00e6berht","alternative names","Saberht"]],"1":[["--------------------\nText: S\u00e6berht of Essex:  616) was a King of Essex (r. \"c\".\nTriplets:<S\u00e6berht of Essex","reigned","616"],["S\u00e6berht of Essex","title","King of Essex"]],"2":[["--------------------\nText: S\u00e6berht of Essex:  604\u00a0\u2013 \"c\".\nTriplets:<S\u00e6berht of Essex","birth year","604"]],"3":[["--------------------\nText: S\u00e6berht of Essex:  616), in succession of his father King Sledd.\nTriplets:<S\u00e6berht of Essex","year of birth","616"],["S\u00e6berht of Essex","relation to parent","King Sledd"]],"4":[["--------------------\n\nText: S\u00e6berht of Essex:\n\nTriplets:<S\u00e6berht of Essex","known as","first East Saxon king"],["S\u00e6berht of Essex","converted to","Christianity"]],"5":[["Bede","died","735"],["S\u00e6berht of Essex","derived his information about","missionary work among East Saxons"],["ere are the triplets extracted directly from the text:\n\n<The principal source","for his reign","Historia Ecclesiastica gentis Anglorum"]],"7":[["--------------------\nText: S\u00e6berht of Essex:\n\nTriplets:<S\u00e6berht of Essex","period","23211)"]]}