{"0":[["ere are the extracted triplets:\n\n<Text: The Tennessee Attorney General (officially, Attorney General and Reporter) is a position within the Tennessee state government.>\nTriplet:<The Tennessee Attorney General","position","Tennessee state government"]],"1":[["--------------------\n<Text: Tennessee Attorney General:  The Attorney General is the chief law enforcement officer and lawyer for Tennessee.>\nTriplets:<Tennessee Attorney General","position","chief law enforcement officer"],["Tennessee Attorney General","position","lawyer"]],"2":[["Tennessee Attorney General","term length","eight years"],["ere are the triplets extracted from the text:\n\n<Tennessee Attorney General","branch","judicial"],["Tennessee Attorney General","appointed by","justices of Tennessee Supreme Court"]],"3":[["ere are the extracted triplets:\n\n<Tennessee Attorney General","office holder","Herbert Slatery"],["Tennessee Attorney General","appointed by","Tennessee Supreme Court"],["Tennessee Attorney General","term length","eight-year term"]],"4":[["ere are the extracted triplets:\n\n<Tennessee Attorney General","swearing in by","Tennessee Governor Bill Haslam"],["Tennessee Attorney General","service began with his swearing in by","October 1, 2014"],["Tennessee Attorney General","sworn in by","Tennessee Governor Bill Haslam"]]}