{"0":[["The Message","status","final"],["Text: \"The Message\" is the third and final single from rapper Nas' second album \"It Was Written\".\nTriplets:<The Message","status","third"]],"1":[["ere are the extracted triplets:\n\n--------------------\n<The Message","producer","Trackmasters"],["<The Message","song sampled from","Sting's \"Shape of My Heart\""]],"3":[["<The Message","did not reach","music charts"],["ere are the triplets extracted from the text:\n\n--------------------\n<The Message","released in","France"]],"5":[["--------------------\n\nText: The Message (Nas song):  \"The Message\" also features vocal samples from Nas's 1994 classic \"N.Y. State Of Mind\" with Nas saying \"I never sleep\/cuz sleep is the cousin of death\".\nTriplets:<The Message","features sample from","N.Y. State Of Mind"]],"7":[["--------------------\n<Text: The Message (Nas song):  And \"Halftime\" after his second verse saying \"There ain't an army that can strike back\".>\nTriplets:<The Message","song lyric","There ain't an army"]]}