{"0":[["The For Carnation","formed year","1994"]],"1":[["--------------------\n<Text: The For Carnation:  The band was formed by Brian McMahan, who is the only constant group member.>\nTriplets:<The For Carnation","formed by","Brian McMahan"],["The For Carnation","constant group member","Brian McMahan"]],"2":[["ere are the extracted triplets:\n\n--------------------\n<The For Carnation","previous band","Slint"]],"3":[["The For Carnation","record labels","Matador Records"],["The For Carnation","record labels","Touch and Go Records"],["--------------------\nText: The For Carnation:  To date they have released two EP and one [self-titled] album: \"Fight Songs\" (Matador Records, 1995), \"Marshmallows\" (Matador, 1996), and \"The For Carnation\" (Touch and Go Records, 2000).\nTriplets:<The For Carnation","released","two EP"],["The For Carnation","released","one album"],["The For Carnation","record labels","Matador"]],"4":[["Runt","released","1997"],["--------------------\n<Text: The For Carnation:  Fight Songs and Marshmallows were compiled into one record, \"Promised Works\", and released by Runt in 1997.>\n\n<Triplets:<The For Carnation","record name","\"Promised Works\""]]}