{"0":[["Urdu Digest","language","Urdu"],["--------------------\nText: Urdu Digest (Urdu: \u200e ) is a monthly Urdu magazine in Pakistan.\nTriplets:<Urdu Digest","published type","monthly"],["Urdu Digest","location","Pakistan"]],"1":[["--------------------\nText: Urdu Digest:  It is first digest in Pakistan and was first published in November 1960 in Lahore.\nTriplets:<Urdu Digest","published in","November 1960"],["Urdu Digest","first in","Pakistan"],["Urdu Digest","place of publication","Lahore"]],"2":[["Scott Derrickson","nationality","America"]],"4":[["ere are the extracted triplets:\n\n--------------------\n<Urdu Digest","performing duty of","character building"],["<Urdu Digest","duration","years"],["<Urdu Digest","for purpose","Pakistanis"]],"5":[["Urdu Digest","goal","promoting national integration"],["--------------------\nText: Urdu Digest:  The magazine also has been serving to strengthen the ideology of Pakistan and promoting national integration.\nTriplets:<Urdu Digest","goal","strengthen the ideology of Pakistan"]],"6":[["<Urdu Digest","publishes translations of","adventure stories"],["ere are the extracted triplets:\n\n<Urdu Digest","publishes translations of","international literary stories"],["<Urdu Digest","publishes translations of","hunting stories"]]}