{"0":[["ere are the triplets extracted directly from the text:\n\n Triplets:<James Bourne","name","Future Boy"],["Volume 1","debut album","ex-Busted and Son of Dork band member"]],"1":[["ere are the extracted triplets:\n\n<Volume 1 (Future Boy album)","released date","June 2010"]],"2":[["James Bourne","describes the album as","100% electronic - and not a rock album"],["**Third Text**\n<Volume 1 (Future Boy album)","produced by","Tommy Henriksen and James Bourne"]],"3":[["Volume 1","release date","1 June"],["ere are the extracted triplets:\n\n<Volume 1","release date","3 May"]],"4":[["--------------------\n<Text: Volume 1 (Future Boy album):  The album's artwork was designed and painted by Paul Karslake.>\nTriplets:<Volume 1 (Future Boy album)","artist","Paul Karslake"]],"5":[["--------------------\nText: Volume 1 (Future Boy album):  Bourne claims that the album will be released on CD at 'some point', but it will depend on 'when he has the cash'.\nTriplets:<Volume 1 (Future Boy album)","release condition","'some point'"],["Volume 1 (Future Boy album)","release condition","'when he has the cash'"]],"6":[["Volume 1 (Future Boy album)","tour","2010 Clubs & Pubs Tour"],["ere are the extracted triplets:\n\n<Volume 1 (Future Boy album)","promoted by","Bourne"],["Volume 1 (Future Boy album)","act for","Twenty Twenty"]]}