{"0":[["ere are the extracted triplets:\n\n<Warren Historic District","location","Pennsylvania"],["<Warren Historic District","located in","Warren"],["<Warren Historic District","type","historic district"]],"1":[["ere are the triplets extracted from the given text:\n\n<Warren Historic District","location","Warren"],["Warren Historic District","type of area","central business district"]],"2":[["Text: Warren Historic District (Warren, Pennsylvania)","styles","Italianate"],["ere are the extracted triplets:\n\n<Text: Warren Historic District (Warren, Pennsylvania)","styles","Greek Revival"]],"3":[["Warren Historic District","Notable buildings include","Conewango Clu"],["Warren Historic District","Notable buildings include","Trinity Episcopal Churc"],["Warren Historic District","Notable buildings include","former Swedish Lutheran Churc"],["Warren Historic District","Notable buildings include","First Presbyterian Churc"],["ere are the extracted triplets:\n\nWarren Historic District","Notable buildings include","the flatiron National City Bank Buildin"],["Warren Historic District","Notable buildings include","Elks Clu"]],"4":[["<Warren Historic District","contributing object","Civil War memorial"],["ere are the extracted triplets:\n\n<Warren Historic District","contributing object","bronze statue"],["<Warren Historic District","contributing object","Soldiers and Sailors Monument"]],"5":[["--------------------\nText: Warren Historic District (Warren, Pennsylvania):  Located in the district and separately listed are the John P. Jefferson House, Struthers Library Building, Warren Armory, Warren County Courthouse, Wetmore House, and Woman's Club of Warren.\nTriplets:<Warren Historic District","located in","Warren, Pennsylvania"],["John P. Jefferson House","Struthers Library Building","Warren Armory"],["Warren County Courthouse","Wetmore House","Woman's Club of Warren"]]}