{"0":[["--------------------\nText: Xeko is a collectible card game revolving around endangered species.\nTriplets:<Xeko","type","collectible card game"],["Xeko","subject matter","endangered species"]],"1":[["--------------------\n\n--------------------\n<Xeko","launched on","2006"]],"2":[["ere are the extracted triplets:\n\n<Xeko","award winner","Toy of the Year"],["Xeko","award winner","National Parenting Center's Seal of Approval"]],"5":[["Xeko","final release","\"Mission: China\""],["--------------------\nText: Xeko:  \"Mission: Indonesia\", was released in 2007, with the final release, \"Mission: China\", was released July 19, 2008.\nTriplets:<Xeko","release date","2007"]],"6":[["--------------------\nText: Xeko:  A total of thirty more missions were planned but never developed.\nTriplets:<Xeko","total number of missions","thirty more"]]}